gym_arenaxlabs/__init__.py
gym_arenaxlabs/envs/__init__.py
gym_arenaxlabs/envs/aiarena/__init__.py
gym_arenaxlabs/envs/aiarena/aiarena.py
gym_arenaxlabs/envs/aiarena/aiarena_docker.py
gym_arenaxlabs/envs/aiarena/aiarena_env.py
gym_arenaxlabs/envs/mujoco/__init__.py
gym_arenaxlabs/envs/mujoco/humanoid_obstacle.py
arenaxlabs_gym-0.0.1.dist-info/LICENSE
arenaxlabs_gym-0.0.1.dist-info/METADATA
arenaxlabs_gym-0.0.1.dist-info/WHEEL
arenaxlabs_gym-0.0.1.dist-info/top_level.txt
arenaxlabs_gym-0.0.1.dist-info/RECORD
